simplejsonseq.py
simplejsonseq-0.2.1.dist-info/LICENSE
simplejsonseq-0.2.1.dist-info/METADATA
simplejsonseq-0.2.1.dist-info/WHEEL
simplejsonseq-0.2.1.dist-info/top_level.txt
simplejsonseq-0.2.1.dist-info/RECORD
